{
  "sections": {
    "5a97e0ca-1580-48d9-aafd-8a9feb3ade1f": {
      "type": "page_banner",
      "settings": {
        "pc_image_url": "https:\/\/cdn.shopify.com\/s\/files\/1\/0257\/5246\/9566\/files\/US_banner_pc.webp?v=1697512558",
        "mol_image_url": "https:\/\/cdn.shopify.com\/s\/files\/1\/0257\/5246\/9566\/files\/US_banner_mo.webp?v=1697512566",
        "image_alt": "The Best Deals AreOne Click Away"
      }
    },
    "2c9bf8f0-ce25-4c99-9bda-06c38ce52758": {
      "type": "gift_card",
      "settings": {
        "section_title": "Purchase a 10% OFF BFCM Gift Card",
        "sub_title": "Get ready for Black Friday by purchasing a 10% off gift card today.",
        "product": "carte-cadeau"
      }
    },
    "ug-product-list": {
      "type": "ug-product-list",
      "settings": {
        "product_list": [
          "ugreen-nexode-chargeur-20w-usb-c-with-mfi-charging-cable",
          "ugreen-nexode-chargeur-30w-usb-c-support-tablette-bureau-reglable-repose",
          "ugreen-nexode-chargeur-65w-usb-c-rapide-3-ports-with-cable",
          "ugreen-65w-chargeur-usb-c-rapide-3-ports-with-cable",
          "30488",
          "40393"
        ],
        "title": "Limited-Time Offers",
        "subtitle": "",
        "section_id": "ug-product-list",
        "pc_product_type": "column",
        "mobile_product_type": "row",
        "product_item_bg_color": "#202422",
        "pc_product_item_img_size": "70%",
        "mobile_product_item_img_size": "100%",
        "pc_row": "3",
        "mobile_row": "2",
        "product_sale_flag": "https:\/\/cdn.shopify.com\/s\/files\/1\/0257\/5246\/9566\/files\/tag_mo.png?v=1697600272",
        "pc_product_sale_width": "4.167vw",
        "mobile_product_sale_width": "12.8vw",
        "pc_padding": "2.083vw 0 6.25vw 0",
        "mobile_padding": "4vw 0 21.333vw 0",
        "need_load_more": false,
        "load_more_default_count": 6,
        "show_sale_flag": true,
        "show_compare": true,
        "show_rating": true,
        "show_learn_btn": true,
        "show_code": true
      }
    },
    "388f7fcd-4e61-4dd4-a908-861b90859d17": {
      "type": "ug-tabs-product-list",
      "blocks": {
        "35c9871c-733f-43d3-b0aa-a3e96b9ef85c": {
          "type": "ug-product-list-tabs",
          "settings": {
            "tabs_title": "Chargers",
            "product_list": [
              "ugreen-20w-chargeur-usb-c-pd-3-0",
              "ugreen-20w-chargeur-usb-c-pd-3-1",
              "ugreen-chargeur-30w-usb-c-pps-pd-3-0",
              "ugreen-chargeur-30w-usb-c-with-cable",
              "ugreen-65w-chargeur-usb-c-rapide-3-ports",
              "ugreen-40w-chargeur-usb-c-2-ports",
              "ugreen-nexode-chargeur-65w-usb-c-rapide-3-ports",
              "ugreen-nexode-200w-gan-chargeur-usb-c-alimentation-100w-et-6-ports"
            ]
          }
        },
        "3f64d1a6-8e13-4c7a-8cfd-a4434dbebf88": {
          "type": "ug-product-list-tabs",
          "settings": {
            "tabs_title": "Hubs & Docking",
            "product_list": [
              "ugreen-10-en-1-hub-usb-c-hdmi-vga-adaptateur",
              "ugreen-6-en-2-adaptateur-hub-usb-c-thunderbolt-3",
              "ugreen-revodok-7-en-1-hub-usb-c-ethernet-hdmi-100w-pd-charge-lecteur-de-carte-sd",
              "ugreen-hub-usb-c-hdmi-4k-60hz-adaptateur-usb-c-rj45-ethernet-supporte",
              "90325",
              "ugreen-revodok-pro-9-en-1-docking-station",
              "ugreen-revodok-hub-usb-c-hdmi-4k-6-en-1-adaptateur-usb-c",
              "ugreen-adaptateur-hub-usb-c-vers-hdmi-4k",
              "ugreen-hub-usb-c-ethernet-hdmi-4k-7-en-1-adaptateur-usb-c",
              "70336"
            ]
          }
        },
        "56de405c-308f-4005-baf2-e1aac394fd05": {
          "type": "ug-product-list-tabs",
          "settings": {
            "tabs_title": "Stands & Holders",
            "product_list": [
              "ugreen-support-telephone-bureau",
              "80708",
              "20435",
              "30488",
              "40393",
              "90396",
              "50323",
              "40907",
              "50853"
            ]
          }
        },
        "75ce9223-3849-4530-97f8-99ba59ce9854": {
          "type": "ug-product-list-tabs",
          "settings": {
            "tabs_title": "Cables",
            "product_list": [
              "60759",
              "60125",
              "70754",
              "20855",
              "50940",
              "10358",
              "50122",
              "70429",
              "ugreen-cable-usb-c-vers-usb-c-pd-charge-rapide-60w-nylon-tresse"
            ]
          }
        },
        "45e517bd-974d-4c65-a935-7e85679c5083": {
          "type": "ug-product-list-tabs",
          "settings": {
            "tabs_title": "Hard Drive",
            "product_list": [
              "ugreen-boitier-m-2-ssd-nvme-usb-3-2-gen-2-10-gbps-aptateur",
              "30848",
              "30847",
              "80556",
              "50743"
            ]
          }
        },
        "6cce2e11-47fb-4d5b-94a8-55c792ce3811": {
          "type": "ug-product-list-tabs",
          "settings": {
            "tabs_title": "Adaptateur Ethernet ",
            "product_list": [
              "30985",
              "20254",
              "50737",
              "20256",
              "50922"
            ]
          }
        }
      },
      "block_order": [
        "35c9871c-733f-43d3-b0aa-a3e96b9ef85c",
        "3f64d1a6-8e13-4c7a-8cfd-a4434dbebf88",
        "56de405c-308f-4005-baf2-e1aac394fd05",
        "75ce9223-3849-4530-97f8-99ba59ce9854",
        "45e517bd-974d-4c65-a935-7e85679c5083",
        "6cce2e11-47fb-4d5b-94a8-55c792ce3811"
      ],
      "settings": {
        "section_id": "sainta-day",
        "section_icon": "",
        "section_title": "Buy More, Save More",
        "sub_title": "",
        "list_all": "6",
        "product_item_bg_color": "#202422",
        "pc_product_item_img_size": "70%",
        "mobile_product_item_img_size": "100%",
        "pc_row": "4",
        "mobile_row": "2",
        "product_sale_flag": "https:\/\/cdn.shopify.com\/s\/files\/1\/0257\/5246\/9566\/files\/tag_mo.png?v=1697600272",
        "pc_product_sale_width": "4.167vw",
        "mobile_product_sale_width": "12.8vw",
        "pc_padding": "2.083vw 0 6.25vw 0",
        "mobile_padding": "4vw 0 21.333vw 0",
        "need_load_more": true,
        "load_more_default_count": 16,
        "show_sale_flag": true,
        "show_compare": true,
        "show_rating": true,
        "show_learn_btn": false,
        "show_code": true
      }
    },
    "30d681da-5279-4baf-9bad-f096bd5258c8": {
      "type": "custom-html",
      "settings": {
        "code": "<style>\n    .shopify-section {\n        background: #141416;\n        margin-top: -1px;\n    }\n\n    .cursor-btns {\n        position: sticky;\n        top: 0;\n        z-index: 2;\n        background: none !important;\n    }\n\n    .cursor-btns .cursor-btn {\n        color: #999 !important;\n        background: #141416 !important;\n        border: 1px solid #666;\n    }\n\n    .cursor-btns .cursor-btn:hover,\n    .cursor-btns .cursor-btn.swiper-slide-thumb-active {\n        color: #000 !important;\n        background: #03F2A6 !important;\n        border: 1px solid #03F2A6;\n        font-weight: 600;\n    }\n\n    .tabs_products_list .contant,\n    .ug-product-list {\n        width: 100%;\n        max-width: 66.667vw !important;\n        margin: 0 auto;\n    }\n\n   \n    .ug-product-buy-btn {\n        background: #FFF !important;\n        color: #000 !important;\n    }\n\n    .ug-product-buy-btn:hover {\n        background: #03F2A6 !important;\n    }\n\n    .ug-product-learn-btn {\n        border: 1px solid #fff !important;\n        color: #fff !important;\n    }\n\n    .ug-product-learn-btn:hover {\n        border: 1px solid #03F2A6 !important;\n        color: #03F2A6 !important;\n    }\n    .ug-product-title {\n            font-weight: 600 !important;\n            color: #FFF !important;\n        }\n\n        .ug-product-price {\n            color: #03F2A6 !important;\n        }\n    .ug-product-list-title,\n    .svg_title h2 {\n        color: #fff !important;\n        display: flex;\n        align-items: center;\n        justify-content: center;\n        gap: 5px;\n    }\n\n    .svg_title svg {\n        display: none;\n    }\n\n    .ug-product-sale {\n        top: -0.625vw !important;\n        left: -0.417vw !important;\n\n    }\n\n    .ug-product-sale-text {\n        width: 2.865vw;\n        color: #000 !important;\n        top: 22% !important;\n        left: 4% !important;\n        font-weight: 700 !important;\n        font-size: 1.25vw !important;\n        transform: rotateZ(315deg) !important;\n        text-align: center;\n    }\n\n    .ug-product-sale-text-percent {\n        font-size: 0.833vw !important;\n        font-weight: 600 !important;\n    }\n\n    .tabs_products_list .ug_product_code {\n        padding: 0.25vw 1.875vw 0.25vw 1vw;\n    }\n\n    .ug-product-list-title::before,\n    .svg_title h2::before {\n        content: '';\n        background: url('https:\/\/cdn.shopify.com\/s\/files\/1\/0257\/5246\/9566\/files\/lightning_left.webp?v=1697635642')center center no-repeat;\n        background-size: 100% 100%;\n        display: inline-block;\n        width: 1.979vw;\n        height: 2.8125vw;\n    }\n\n    .ug-product-list-title::after,\n    .svg_title h2::after {\n        content: '';\n        background: url('https:\/\/cdn.shopify.com\/s\/files\/1\/0257\/5246\/9566\/files\/lightning_right.webp?v=1697635854')center center no-repeat;\n        background-size: 100% 100%;\n        display: inline-block;\n        width: 1.979vw;\n        height: 2.8125vw;\n    }\n    #sainta-day .ug-product-review{\n        display: none;\n    }\n    @media (min-width:768px) {\n        .ug-product-title {\n            font-size: 1.042vw!important;\n            line-height: 1.5625vw!important;\n            height: 3vw!important;\n        }\n\n        .ug-product-price {\n            font-size: 1.354vw!important;\n        }\n        .ug-product-compare_at_price{\n            font-size: 0.833vw!important;\n        }\n    }\n    @media (max-width:768px) {\n\n        .tabs_products_list .contant,\n        .ug-product-list {\n            max-width: 100% !important;\n        }\n\n        .ug-product-list-title {\n            margin-bottom: 30px !important;\n        }\n        .ug-product-sale{\n            top: -1.5vw !important;\n            left: -1vw !important;\n        }\n        .ug-product-sale-text {\n            font-size: 4.267vw !important;\n            width: 10.667vw;\n            top: 20% !important;\n            left: -5% !important;\n        }\n\n        .ug-product-sale-text-percent {\n            font-size: 12px!important;\n        }\n\n        .ug_product_code {\n            background: none;\n            padding: 0;\n            margin: 10px 0 0 0;\n        }\n\n        .ug_product_code p {\n            font-size: 12px;\n            color: #999;\n        }\n\n        .ug_product_code button {\n            font-size: 12px;\n            font-weight: 500;\n        }\n\n        .cursor-btns .swiper-wrapper {\n            justify-content: flex-start !important;\n        }\n\n        .cursor-btns .cursor-btn {\n            padding: 0 !important;\n            height: 40px;\n            display: flex;\n            align-items: center;\n            justify-content: center;\n        }\n\n        .svg_title h2 {\n            font-size: 24px !important;\n            padding: 0 0 15px 0 !important;\n        }\n\n        .svg_title p {\n            display: none;\n        }\n\n        .ug-product-list-title::before,\n        .svg_title h2::before {\n            width: 8vw;\n            height: 11.200vw;\n        }\n\n        .ug-product-list-title::after,\n        .svg_title h2::after {\n            width: 8vw;\n            height: 11.200vw;\n        }\n    }\n<\/style>",
        "layout": "t4s-container-fluid",
        "cl_bg": "",
        "cl_bg_gradient": "",
        "mg": "",
        "pd": "",
        "mg_mb": "",
        "pd_mb": "",
        "use_cus_css": false,
        "code_cus_css": ""
      }
    }
  },
  "order": [
    "5a97e0ca-1580-48d9-aafd-8a9feb3ade1f",
    "2c9bf8f0-ce25-4c99-9bda-06c38ce52758",
    "ug-product-list",
    "388f7fcd-4e61-4dd4-a908-861b90859d17",
    "30d681da-5279-4baf-9bad-f096bd5258c8"
  ]
}
